
{
   "methods" : {
      "hashRedemptionIntent(bytes32,address,uint256,uint256,uint256)" : {
         "details" : "Returns hash of _uuid, _account, _accountNonce, _amountUT, _escrowUnlockHeight",
         "params" : {
            "_account" : "account",
            "_accountNonce" : "accountNonce",
            "_amountUT" : "amountUT",
            "_escrowUnlockHeight" : "escrowUnlockHeight",
            "_uuid" : "uuid"
         },
         "return" : "bytes32"
      },
      "hashStakingIntent(bytes32,address,uint256,address,uint256,uint256,uint256)" : {
         "details" : "Returns hash of _uuid, _account, _accountNonce, _beneficiary, _amountST, _amountUT, _escrowUnlockHeight",
         "params" : {
            "_account" : "account",
            "_accountNonce" : "accountNonce",
            "_amountST" : "amountST",
            "_amountUT" : "amountUT",
            "_beneficiary" : "beneficiary",
            "_escrowUnlockHeight" : "escrowUnlockHeight",
            "_uuid" : "uuid"
         },
         "return" : "bytes32"
      },
      "hashUuid(string,string,uint256,uint256,address,uint256)" : {
         "details" : "Returns hash of _symbol, _name, _chainIdValue, _chainIdUtility, _openSTUtility, _conversionRate",
         "params" : {
            "_chainIdUtility" : "chainIdUtility",
            "_chainIdValue" : "chainIdValue",
            "_conversionRate" : "conversionRate",
            "_name" : "name",
            "_openSTUtility" : "openSTUtility",
            "_symbol" : "symbol"
         },
         "return" : "bytes32"
      }
   },
   "title" : "Hasher - Protocol hash functions"
}

